Metadata-Version: 2.1
Name: ode-style
Version: 0.0.10
Summary: A framework to drive a clean code
Author: v2SoftwareHouse
